{
  "trials": [
    {"question_number": 1 , "trial_type" : "practice", "trial_section": "<matching>", "stimulus": {"digit": "dig3.png", "symbol": "sym3.png", "is_match": 1}},
    {"question_number": 2 , "trial_type" : "practice", "trial_section": "<matching>", "stimulus": {"digit": "dig2.png", "symbol": "sym2.png", "is_match": 1}},
    {"question_number": 3 , "trial_type" : "practice", "trial_section": "<matching>", "stimulus": {"digit": "dig1.png", "symbol": "sym1.png", "is_match": 1}},
    {"question_number": 4 , "trial_type" : "practice", "trial_section": "<matching>", "stimulus": {"digit": "dig7.png", "symbol": "sym2.png", "is_match": 0}},
    {"question_number": 5 , "trial_type" : "practice", "trial_section": "<matching>", "stimulus": {"digit": "dig4.png", "symbol": "sym3.png", "is_match": 0}},
    {"question_number": 1 , "trial_type" : "test", "trial_section": "<matching>", "stimulus": {"digit": "dig3.png", "symbol": "sym3.png", "is_match": 1}},
    {"question_number": 2 , "trial_type" : "test", "trial_section": "<matching>", "stimulus": {"digit": "dig7.png", "symbol": "sym9.png", "is_match": 0}},
    {"question_number": 3 , "trial_type" : "test", "trial_section": "<matching>", "stimulus": {"digit": "dig7.png", "symbol": "sym7.png", "is_match": 1}},
    {"question_number": 4 , "trial_type" : "test", "trial_section": "<matching>", "stimulus": {"digit": "dig9.png", "symbol": "sym4.png", "is_match": 0}},
    {"question_number": 5 , "trial_type" : "test", "trial_section": "<matching>", "stimulus": {"digit": "dig5.png", "symbol": "sym5.png", "is_match": 1}},
    {"question_number": 6 , "trial_type" : "test", "trial_section": "<matching>", "stimulus": {"digit": "dig4.png", "symbol": "sym4.png", "is_match": 1}},
    {"question_number": 7 , "trial_type" : "test", "trial_section": "<matching>", "stimulus": {"digit": "dig1.png", "symbol": "sym1.png", "is_match": 1}},
    {"question_number": 8 , "trial_type" : "test", "trial_section": "<matching>", "stimulus": {"digit": "dig8.png", "symbol": "sym7.png", "is_match": 0}},
    {"question_number": 9 , "trial_type" : "test", "trial_section": "<matching>", "stimulus": {"digit": "dig2.png", "symbol": "sym3.png", "is_match": 0}},
    {"question_number": 10 , "trial_type" : "test", "trial_section": "<matching>", "stimulus": {"digit": "dig8.png", "symbol": "sym8.png", "is_match": 1}},
    {"question_number": 11 , "trial_type" : "test", "trial_section": "<matching>", "stimulus": {"digit": "dig1.png", "symbol": "sym6.png", "is_match": 0}},
    {"question_number": 12 , "trial_type" : "test", "trial_section": "<matching>", "stimulus": {"digit": "dig3.png", "symbol": "sym8.png", "is_match": 0}},
    {"question_number": 13 , "trial_type" : "test", "trial_section": "<matching>", "stimulus": {"digit": "dig4.png", "symbol": "sym5.png", "is_match": 0}},
    {"question_number": 14 , "trial_type" : "test", "trial_section": "<matching>", "stimulus": {"digit": "dig2.png", "symbol": "sym2.png", "is_match": 1}},
    {"question_number": 15 , "trial_type" : "test", "trial_section": "<matching>", "stimulus": {"digit": "dig6.png", "symbol": "sym1.png", "is_match": 0}},
    {"question_number": 16 , "trial_type" : "test", "trial_section": "<matching>", "stimulus": {"digit": "dig9.png", "symbol": "sym9.png", "is_match": 1}},
    {"question_number": 17 , "trial_type" : "test", "trial_section": "<matching>", "stimulus": {"digit": "dig6.png", "symbol": "sym6.png", "is_match": 1}},
    {"question_number": 18 , "trial_type" : "test", "trial_section": "<matching>", "stimulus": {"digit": "dig5.png", "symbol": "sym2.png", "is_match": 0}},
    {"question_number": 19 , "trial_type" : "test", "trial_section": "<matching>", "stimulus": {"digit": "dig6.png", "symbol": "sym6.png", "is_match": 1}},
    {"question_number": 20 , "trial_type" : "test", "trial_section": "<matching>", "stimulus": {"digit": "dig5.png", "symbol": "sym3.png", "is_match": 0}},
    {"question_number": 21 , "trial_type" : "test", "trial_section": "<matching>", "stimulus": {"digit": "dig7.png", "symbol": "sym7.png", "is_match": 1}},
    {"question_number": 22 , "trial_type" : "test", "trial_section": "<matching>", "stimulus": {"digit": "dig6.png", "symbol": "sym1.png", "is_match": 0}},
    {"question_number": 23 , "trial_type" : "test", "trial_section": "<matching>", "stimulus": {"digit": "dig7.png", "symbol": "sym4.png", "is_match": 0}},
    {"question_number": 24 , "trial_type" : "test", "trial_section": "<matching>", "stimulus": {"digit": "dig3.png", "symbol": "sym3.png", "is_match": 1}},
    {"question_number": 25 , "trial_type" : "test", "trial_section": "<matching>", "stimulus": {"digit": "dig3.png", "symbol": "sym8.png", "is_match": 0}},
    {"question_number": 26 , "trial_type" : "test", "trial_section": "<matching>", "stimulus": {"digit": "dig5.png", "symbol": "sym5.png", "is_match": 1}},
    {"question_number": 27 , "trial_type" : "test", "trial_section": "<matching>", "stimulus": {"digit": "dig4.png", "symbol": "sym6.png", "is_match": 0}},
    {"question_number": 28 , "trial_type" : "test", "trial_section": "<matching>", "stimulus": {"digit": "dig9.png", "symbol": "sym9.png", "is_match": 1}},
    {"question_number": 29 , "trial_type" : "test", "trial_section": "<matching>", "stimulus": {"digit": "dig8.png", "symbol": "sym8.png", "is_match": 1}},
    {"question_number": 30 , "trial_type" : "test", "trial_section": "<matching>", "stimulus": {"digit": "dig2.png", "symbol": "sym7.png", "is_match": 0}},
    {"question_number": 31 , "trial_type" : "test", "trial_section": "<matching>", "stimulus": {"digit": "dig9.png", "symbol": "sym2.png", "is_match": 0}},
    {"question_number": 32 , "trial_type" : "test", "trial_section": "<matching>", "stimulus": {"digit": "dig4.png", "symbol": "sym4.png", "is_match": 1}},
    {"question_number": 33 , "trial_type" : "test", "trial_section": "<matching>", "stimulus": {"digit": "dig8.png", "symbol": "sym9.png", "is_match": 0}},
    {"question_number": 34 , "trial_type" : "test", "trial_section": "<matching>", "stimulus": {"digit": "dig1.png", "symbol": "sym5.png", "is_match": 0}},
    {"question_number": 35 , "trial_type" : "test", "trial_section": "<matching>", "stimulus": {"digit": "dig2.png", "symbol": "sym2.png", "is_match": 1}},
    {"question_number": 36 , "trial_type" : "test", "trial_section": "<matching>", "stimulus": {"digit": "dig1.png", "symbol": "sym1.png", "is_match": 1}},
    {"question_number": 37 , "trial_type" : "test", "trial_section": "<matching>", "stimulus": {"digit": "dig7.png", "symbol": "sym9.png", "is_match": 0}},
    {"question_number": 38 , "trial_type" : "test", "trial_section": "<matching>", "stimulus": {"digit": "dig9.png", "symbol": "sym9.png", "is_match": 1}},
    {"question_number": 39 , "trial_type" : "test", "trial_section": "<matching>", "stimulus": {"digit": "dig1.png", "symbol": "sym1.png", "is_match": 1}},
    {"question_number": 40 , "trial_type" : "test", "trial_section": "<matching>", "stimulus": {"digit": "dig4.png", "symbol": "sym4.png", "is_match": 1}},
    {"question_number": 41 , "trial_type" : "test", "trial_section": "<matching>", "stimulus": {"digit": "dig1.png", "symbol": "sym7.png", "is_match": 0}},
    {"question_number": 42 , "trial_type" : "test", "trial_section": "<matching>", "stimulus": {"digit": "dig3.png", "symbol": "sym3.png", "is_match": 1}},
    {"question_number": 43 , "trial_type" : "test", "trial_section": "<matching>", "stimulus": {"digit": "dig7.png", "symbol": "sym7.png", "is_match": 1}},
    {"question_number": 44 , "trial_type" : "test", "trial_section": "<matching>", "stimulus": {"digit": "dig9.png", "symbol": "sym8.png", "is_match": 0}},
    {"question_number": 45 , "trial_type" : "test", "trial_section": "<matching>", "stimulus": {"digit": "dig8.png", "symbol": "sym4.png", "is_match": 0}},
    {"question_number": 46 , "trial_type" : "test", "trial_section": "<matching>", "stimulus": {"digit": "dig8.png", "symbol": "sym8.png", "is_match": 1}},
    {"question_number": 47 , "trial_type" : "test", "trial_section": "<matching>", "stimulus": {"digit": "dig3.png", "symbol": "sym1.png", "is_match": 0}},
    {"question_number": 48 , "trial_type" : "test", "trial_section": "<matching>", "stimulus": {"digit": "dig2.png", "symbol": "sym2.png", "is_match": 1}},
    {"question_number": 49 , "trial_type" : "test", "trial_section": "<matching>", "stimulus": {"digit": "dig4.png", "symbol": "sym3.png", "is_match": 0}},
    {"question_number": 50 , "trial_type" : "test", "trial_section": "<matching>", "stimulus": {"digit": "dig2.png", "symbol": "sym6.png", "is_match": 0}},
    {"question_number": 51 , "trial_type" : "test", "trial_section": "<matching>", "stimulus": {"digit": "dig6.png", "symbol": "sym5.png", "is_match": 0}},
    {"question_number": 52 , "trial_type" : "test", "trial_section": "<matching>", "stimulus": {"digit": "dig5.png", "symbol": "sym2.png", "is_match": 0}},
    {"question_number": 53 , "trial_type" : "test", "trial_section": "<matching>", "stimulus": {"digit": "dig5.png", "symbol": "sym5.png", "is_match": 1}},
    {"question_number": 54 , "trial_type" : "test", "trial_section": "<matching>", "stimulus": {"digit": "dig6.png", "symbol": "sym6.png", "is_match": 1}},
    {"question_number": 56, "trial_type" : "test", "trial_section": "<memory>", "stimulus": {"symbol": "sym1.png"}},
    {"question_number": 57, "trial_type" : "test", "trial_section": "<memory>", "stimulus": {"symbol": "sym2.png"}},
    {"question_number": 58, "trial_type" : "test", "trial_section": "<memory>", "stimulus": {"symbol": "sym3.png"}},
    {"question_number": 59, "trial_type" : "test", "trial_section": "<memory>", "stimulus": {"symbol": "sym4.png"}},
    {"question_number": 60, "trial_type" : "test", "trial_section": "<memory>", "stimulus": {"symbol": "sym5.png"}},
    {"question_number": 61, "trial_type" : "test", "trial_section": "<memory>", "stimulus": {"symbol": "sym6.png"}},
    {"question_number": 62, "trial_type" : "test", "trial_section": "<memory>", "stimulus": {"symbol": "sym7.png"}},
    {"question_number": 63, "trial_type" : "test", "trial_section": "<memory>", "stimulus": {"symbol": "sym8.png"}},
    {"question_number": 64, "trial_type" : "test", "trial_section": "<memory>", "stimulus": {"symbol": "sym9.png"}}
  ]
}
