{
  "trials": [
{"question_number": 1 , "responses":["I"], "stimulus":{"x": 188 , "y": 3 , "w": 407 , "h": 368 },"trial_type": "practice"},
{"question_number": 2 , "responses":["II"], "stimulus":{"x": 5.5 , "y": 44.8 , "w": 350 , "h": 333 },"trial_type": "practice"},
{"question_number": 3 , "responses":["III"], "stimulus":{"x": 275.4 , "y": 0.55 , "w": 323 , "h": 306 },"trial_type": "practice"},
{"question_number": 4 , "responses":["IV"], "stimulus":{"x": 5 , "y": 4 , "w": 302 , "h": 288 },"trial_type": "practice"},
{"question_number": 5 , "responses":["V"], "stimulus":{"x": 299 , "y": 88 , "w": 293 , "h": 265 },"trial_type": "practice"},
{"question_number": 6 , "responses":["VI"], "stimulus":{"x": 4.6 , "y": 97.6 , "w": 261 , "h": 244 },"trial_type": "practice"},
{"question_number": 7 , "responses":["VII"], "stimulus":{"x": 332.1 , "y": 11.8 , "w": 255 , "h": 224 },"trial_type": "practice"},
{"question_number": 8 , "responses":["VIII"], "stimulus":{"x": 5.2 , "y": 45.1 , "w": 232 , "h": 194 },"trial_type": "practice"},
{"question_number": 9 , "responses":["IX"], "stimulus":{"x": 365.6 , "y": 194.7 , "w": 226 , "h": 181 },"trial_type": "practice"},
{"question_number": 10 , "responses":["X"], "stimulus":{"x": 380.1 , "y": 3.2 , "w": 214.1 , "h": 166 },"trial_type": "practice"},
{"question_number": 11 , "responses":["XI"], "stimulus":{"x": 4.8 , "y": 5.8 , "w": 198 , "h": 147 },"trial_type": "practice"},
{"question_number": 12 , "responses":["XII"], "stimulus":{"x": 415.8 , "y": 222.85 , "w": 176.9 , "h": 124 },"trial_type": "practice"},
{"question_number": 13 , "responses":["XIII"], "stimulus":{"x": 113.3 , "y": 138.3 , "w": 157 , "h": 102 },"trial_type": "practice"},
{"question_number": 14 , "responses":["XIV"], "stimulus":{"x": 470.9 , "y": 0.8 , "w": 126.9 , "h": 80 },"trial_type": "practice"},
{"question_number": 15 , "responses":["XV"], "stimulus":{"x": 44.4 , "y": 250.3 , "w": 115 , "h": 59 },"trial_type": "practice"},
{"question_number": 16 , "responses":["XVI"], "stimulus":{"x": 263.9 , "y": 17.9 , "w": 94 , "h": 40 },"trial_type": "practice"},
{"question_number": 17 , "responses":["XVII"], "stimulus":{"x": 366.4 , "y": 286.4 , "w": 76 , "h": 36 },"trial_type": "practice"},
{"question_number": 18 , "responses":["XVIII"], "stimulus":{"x": 223.8 , "y": 11.9 , "w": 57.1 , "h": 30 },"trial_type": "practice"},
{"question_number": 19 , "responses":["XIX"], "stimulus":{"x": 558.4 , "y": 25.4 , "w": 39 , "h": 25 },"trial_type": "practice"},
{"question_number": 20 , "responses":["XX"], "stimulus":{"x": 123.45 , "y": 143.45 , "w": 21.1 , "h": 21.1 },"trial_type": "practice"},
{"question_number": 21 , "responses":["I"], "stimulus":{"x": 187.8 , "y": 3.05 , "w": 407.1 , "h": 367.9 }, "trial_type": "test"},
{"question_number": 22 , "responses":["II"], "stimulus":{"x": 5.5 , "y": 44.8 , "w": 350 , "h": 333 }, "trial_type": "test"},
{"question_number": 23 , "responses":["III"], "stimulus":{"x": 275.4 , "y": 0.55 , "w": 323 , "h": 306 }, "trial_type": "test"},
{"question_number": 24 , "responses":["IV"], "stimulus":{"x": 5.05 , "y": 4 , "w": 302 , "h": 288 }, "trial_type": "test"},
{"question_number": 25 , "responses":["V"], "stimulus":{"x": 299 , "y": 88 , "w": 293 , "h": 265 }, "trial_type": "test"},
{"question_number": 26 , "responses":["VI"], "stimulus":{"x": 4.6 , "y": 97.6 , "w": 261 , "h": 244 }, "trial_type": "test"},
{"question_number": 27 , "responses":["VII"], "stimulus":{"x": 339.1 , "y": 15.2 , "w": 255 , "h": 224 }, "trial_type": "test"},
{"question_number": 28 , "responses":["VIII"], "stimulus":{"x": 5.2 , "y": 45.1 , "w": 232 , "h": 194 }, "trial_type": "test"},
{"question_number": 29 , "responses":["IX"], "stimulus":{"x": 365.6 , "y": 194.7 , "w": 226 , "h": 181 }, "trial_type": "test"},
{"question_number": 30 , "responses":["X"], "stimulus":{"x": 380.1 , "y": 3.2 , "w": 214.1 , "h": 166 }, "trial_type": "test"},
{"question_number": 31 , "responses":["XI"], "stimulus":{"x": 4.8 , "y": 5.8 , "w": 198 , "h": 147 }, "trial_type": "test"},
{"question_number": 32 , "responses":["XII"], "stimulus":{"x": 415.8 , "y": 222.85 , "w": 176.9 , "h": 124 }, "trial_type": "test"},
{"question_number": 33 , "responses":["XIII"], "stimulus":{"x": 113.3 , "y": 138.3 , "w": 157 , "h": 102 }, "trial_type": "test"},
{"question_number": 34 , "responses":["XIV"], "stimulus":{"x": 470.9 , "y": 0.8 , "w": 126.9 , "h": 80 }, "trial_type": "test"},
{"question_number": 35 , "responses":["XV"], "stimulus":{"x": 44.4 , "y": 250.3 , "w": 115 , "h": 59 }, "trial_type": "test"},
{"question_number": 36 , "responses":["XVI"], "stimulus":{"x": 263.9 , "y": 17.9 , "w": 94 , "h": 40 }, "trial_type": "test"},
{"question_number": 37 , "responses":["XVII"], "stimulus":{"x": 366.4 , "y": 286.4 , "w": 76 , "h": 36 }, "trial_type": "test"},
{"question_number": 38 , "responses":["XVIII"], "stimulus":{"x": 223.8 , "y": 11.9 , "w": 57.1 , "h": 30 }, "trial_type": "test"},
{"question_number": 39 , "responses":["XIX"], "stimulus":{"x": 533.4 , "y": 25.4 , "w": 39 , "h": 25 }, "trial_type": "test"},
{"question_number": 40 , "responses":["XX"], "stimulus":{"x": 123.45 , "y": 143.45 , "w": 21.1 , "h": 21.1}, "trial_type": "test"}
]
}
