{
  "trials": [
{"question_number":1, "stimulus":"D", "trial_type": "practice", "trial_section": "<0_back_practice>"},
{"question_number":2, "stimulus":"X", "trial_type": "practice", "trial_section": "<0_back_practice>", "correct_response":32},
{"question_number":3, "stimulus":"F", "trial_type": "practice", "trial_section": "<0_back_practice>"},
{"question_number":4, "stimulus":"L", "trial_type": "practice", "trial_section": "<0_back_practice>"},
{"question_number":5, "stimulus":"X", "trial_type": "practice", "trial_section": "<0_back_practice>", "correct_response":32},
{"question_number":6, "stimulus":"V", "trial_type": "practice", "trial_section": "<0_back_practice>"},
{"question_number":7, "stimulus":"S", "trial_type": "practice", "trial_section": "<0_back_practice>"},
{"question_number":8, "stimulus":"B", "trial_type": "practice", "trial_section": "<0_back_practice>"},
{"question_number":9, "stimulus":"X", "trial_type": "practice", "trial_section": "<0_back_practice>", "correct_response":32},
{"question_number":10, "stimulus":"H", "trial_type": "practice", "trial_section": "<0_back_practice>"},
{"question_number":11, "stimulus":"T", "trial_type": "practice", "trial_section": "<0_back_practice>"},
{"question_number":1, "stimulus":"N", "trial_type": "practice", "trial_section": "<1_back_practice>"},
{"question_number":2, "stimulus":"G", "trial_type": "practice", "trial_section": "<1_back_practice>"},
{"question_number":3, "stimulus":"G", "trial_type": "practice", "trial_section": "<1_back_practice>", "correct_response":32},
{"question_number":4, "stimulus":"T", "trial_type": "practice", "trial_section": "<1_back_practice>"},
{"question_number":5, "stimulus":"F", "trial_type": "practice", "trial_section": "<1_back_practice>"},
{"question_number":6, "stimulus":"D", "trial_type": "practice", "trial_section": "<1_back_practice>"},
{"question_number":7, "stimulus":"R", "trial_type": "practice", "trial_section": "<1_back_practice>"},
{"question_number":8, "stimulus":"R", "trial_type": "practice", "trial_section": "<1_back_practice>", "correct_response":32},
{"question_number":9, "stimulus":"P", "trial_type": "practice", "trial_section": "<1_back_practice>"},
{"question_number":10, "stimulus":"P", "trial_type": "practice", "trial_section": "<1_back_practice>", "correct_response":32},
{"question_number":11, "stimulus":"C", "trial_type": "practice", "trial_section": "<1_back_practice>"},
{"question_number":1, "stimulus": "K", "trial_type": "practice", "trial_section": "<2_back_practice>"},
{"question_number":2, "stimulus": "T", "trial_type": "practice", "trial_section": "<2_back_practice>"},
{"question_number":3, "stimulus": "K", "trial_type": "practice", "trial_section": "<2_back_practice>", "correct_response": 32},
{"question_number":4, "stimulus": "S", "trial_type": "practice", "trial_section": "<2_back_practice>"},
{"question_number":5, "stimulus": "Z", "trial_type": "practice", "trial_section": "<2_back_practice>"},
{"question_number":6, "stimulus": "L", "trial_type": "practice", "trial_section": "<2_back_practice>"},
{"question_number":7, "stimulus": "Z", "trial_type": "practice", "trial_section": "<2_back_practice>", "correct_response": 32},
{"question_number":8, "stimulus": "H", "trial_type": "practice", "trial_section": "<2_back_practice>"},
{"question_number":9, "stimulus": "Z", "trial_type": "practice", "trial_section": "<2_back_practice>", "correct_response": 32},
{"question_number":10, "stimulus": "B", "trial_type": "practice", "trial_section": "<2_back_practice>"},
{"question_number":11, "stimulus": "J", "trial_type": "practice", "trial_section": "<2_back_practice>"},
{"question_number":12, "stimulus": "M", "trial_type": "practice", "trial_section": "<2_back_practice>"},
{"question_number":13, "stimulus": "J", "trial_type": "practice", "trial_section": "<2_back_practice>", "correct_response": 32},
{"question_number":14, "stimulus": "D", "trial_type": "practice", "trial_section": "<2_back_practice>"},
{"question_number":15, "stimulus": "C", "trial_type": "practice", "trial_section": "<2_back_practice>"},
{"question_number":1, "stimulus":"F", "trial_type": "test", "trial_section": "<0_back_1>"},
{"question_number":2, "stimulus":"T", "trial_type": "test", "trial_section": "<0_back_1>"},
{"question_number":3, "stimulus":"X", "trial_type": "test", "trial_section": "<0_back_1>"},
{"question_number":4, "stimulus":"X", "trial_type": "test", "trial_section": "<0_back_1>"},
{"question_number":5, "stimulus":"B", "trial_type": "test", "trial_section": "<0_back_1>"},
{"question_number":6, "stimulus":"X", "trial_type": "test", "trial_section": "<0_back_1>"},
{"question_number":7, "stimulus":"N", "trial_type": "test", "trial_section": "<0_back_1>"},
{"question_number":8, "stimulus":"Z", "trial_type": "test", "trial_section": "<0_back_1>"},
{"question_number":9, "stimulus":"M", "trial_type": "test", "trial_section": "<0_back_1>"},
{"question_number":10, "stimulus":"H", "trial_type": "test", "trial_section": "<0_back_1>"},
{"question_number":11, "stimulus":"X", "trial_type": "test", "trial_section": "<0_back_1>"},
{"question_number":12, "stimulus":"C", "trial_type": "test", "trial_section": "<0_back_1>"},
{"question_number":13, "stimulus":"Q", "trial_type": "test", "trial_section": "<0_back_1>"},
{"question_number":14, "stimulus":"J", "trial_type": "test", "trial_section": "<0_back_1>"},
{"question_number":15, "stimulus":"X", "trial_type": "test", "trial_section": "<0_back_1>"},
{"question_number":16, "stimulus":"S", "trial_type": "test", "trial_section": "<1_back_1>"},
{"question_number":17, "stimulus":"Z", "trial_type": "test", "trial_section": "<1_back_1>"},
{"question_number":18, "stimulus":"G", "trial_type": "test", "trial_section": "<1_back_1>"},
{"question_number":19, "stimulus":"G", "trial_type": "test", "trial_section": "<1_back_1>"},
{"question_number":20, "stimulus":"L", "trial_type": "test", "trial_section": "<1_back_1>"},
{"question_number":21, "stimulus":"V", "trial_type": "test", "trial_section": "<1_back_1>"},
{"question_number":22, "stimulus":"V", "trial_type": "test", "trial_section": "<1_back_1>"},
{"question_number":23, "stimulus":"J", "trial_type": "test", "trial_section": "<1_back_1>"},
{"question_number":24, "stimulus":"J", "trial_type": "test", "trial_section": "<1_back_1>"},
{"question_number":25, "stimulus":"D", "trial_type": "test", "trial_section": "<1_back_1>"},
{"question_number":26, "stimulus":"Q", "trial_type": "test", "trial_section": "<1_back_1>"},
{"question_number":27, "stimulus":"Q", "trial_type": "test", "trial_section": "<1_back_1>"},
{"question_number":28, "stimulus":"B", "trial_type": "test", "trial_section": "<1_back_1>"},
{"question_number":29, "stimulus":"N", "trial_type": "test", "trial_section": "<1_back_1>"},
{"question_number":30, "stimulus":"N","trial_type": "test", "trial_section": "<1_back_1>"},
{ "question_number":31, "stimulus": "J", "trial_type": "test", "trial_section": "<2_back_1>" },
{ "question_number":32, "stimulus": "S", "trial_type": "test", "trial_section": "<2_back_1>" },
{ "question_number":33, "stimulus": "J", "trial_type": "test", "trial_section": "<2_back_1>" },
{ "question_number":34, "stimulus": "S", "trial_type": "test", "trial_section": "<2_back_1>" },
{ "question_number":35, "stimulus": "R", "trial_type": "test", "trial_section": "<2_back_1>" },
{ "question_number":36, "stimulus": "D", "trial_type": "test", "trial_section": "<2_back_1>" },
{ "question_number":37, "stimulus": "K", "trial_type": "test", "trial_section": "<2_back_1>" },
{ "question_number":38, "stimulus": "D", "trial_type": "test", "trial_section": "<2_back_1>" },
{ "question_number":39, "stimulus": "B", "trial_type": "test", "trial_section": "<2_back_1>" },
{ "question_number":40, "stimulus": "T", "trial_type": "test", "trial_section": "<2_back_1>" },
{ "question_number":41, "stimulus": "B", "trial_type": "test", "trial_section": "<2_back_1>" },
{ "question_number":42, "stimulus": "V", "trial_type": "test", "trial_section": "<2_back_1>" },
{ "question_number":43, "stimulus": "S", "trial_type": "test", "trial_section": "<2_back_1>" },
{ "question_number":44, "stimulus": "V", "trial_type": "test", "trial_section": "<2_back_1>" },
{ "question_number":45, "stimulus": "L", "trial_type": "test", "trial_section": "<2_back_1>" },
{"question_number":46, "stimulus":"C", "trial_type": "test", "trial_section": "<1_back_2>"},
{"question_number":47, "stimulus":"C", "trial_type": "test", "trial_section": "<1_back_2>"},
{"question_number":48, "stimulus":"T", "trial_type": "test", "trial_section": "<1_back_2>"},
{"question_number":49, "stimulus":"T", "trial_type": "test", "trial_section": "<1_back_2>"},
{"question_number":50, "stimulus":"W", "trial_type": "test", "trial_section": "<1_back_2>"},
{"question_number":51, "stimulus":"K", "trial_type": "test", "trial_section": "<1_back_2>"},
{"question_number":52, "stimulus":"R", "trial_type": "test", "trial_section": "<1_back_2>"},
{"question_number":53, "stimulus":"R", "trial_type": "test", "trial_section": "<1_back_2>"},
{"question_number":54, "stimulus":"F", "trial_type": "test", "trial_section": "<1_back_2>"},
{"question_number":55, "stimulus":"F", "trial_type": "test", "trial_section": "<1_back_2>"},
{"question_number":56, "stimulus":"M", "trial_type": "test", "trial_section": "<1_back_2>"},
{"question_number":57, "stimulus":"P", "trial_type": "test", "trial_section": "<1_back_2>"},
{"question_number":58, "stimulus":"Z", "trial_type": "test", "trial_section": "<1_back_2>"},
{"question_number":59, "stimulus":"H", "trial_type": "test", "trial_section": "<1_back_2>"},
{"question_number":60, "stimulus":"H", "trial_type": "test", "trial_section": "<1_back_2>"},
{ "question_number":61, "stimulus": "G", "trial_type": "test", "trial_section": "<2_back_2>" },
{ "question_number":62, "stimulus": "J", "trial_type": "test", "trial_section": "<2_back_2>" },
{ "question_number":63, "stimulus": "G", "trial_type": "test", "trial_section": "<2_back_2>" },
{ "question_number":64, "stimulus": "Z", "trial_type": "test", "trial_section": "<2_back_2>" },
{ "question_number":65, "stimulus": "T", "trial_type": "test", "trial_section": "<2_back_2>" },
{ "question_number":66, "stimulus": "F", "trial_type": "test", "trial_section": "<2_back_2>" },
{ "question_number":67, "stimulus": "P", "trial_type": "test", "trial_section": "<2_back_2>" },
{ "question_number":68, "stimulus": "F", "trial_type": "test", "trial_section": "<2_back_2>" },
{ "question_number":69, "stimulus": "P", "trial_type": "test", "trial_section": "<2_back_2>" },
{ "question_number":70, "stimulus": "S", "trial_type": "test", "trial_section": "<2_back_2>" },
{ "question_number":71, "stimulus": "P", "trial_type": "test", "trial_section": "<2_back_2>" },
{ "question_number":72, "stimulus": "N", "trial_type": "test", "trial_section": "<2_back_2>" },
{ "question_number":73, "stimulus": "R", "trial_type": "test", "trial_section": "<2_back_2>" },
{ "question_number":74, "stimulus": "N", "trial_type": "test", "trial_section": "<2_back_2>" },
{ "question_number":75, "stimulus": "K", "trial_type": "test", "trial_section": "<2_back_2>" },
{"question_number":76, "stimulus": "V", "trial_type": "test", "trial_section": "<0_back_2>" },
{"question_number":77, "stimulus": "B", "trial_type": "test", "trial_section": "<0_back_2>" },
{"question_number":78, "stimulus": "N", "trial_type": "test", "trial_section": "<0_back_2>" },
{"question_number":79, "stimulus": "X", "trial_type": "test", "trial_section": "<0_back_2>" },
{"question_number":80, "stimulus": "C", "trial_type": "test", "trial_section": "<0_back_2>" },
{"question_number":81, "stimulus": "T", "trial_type": "test", "trial_section": "<0_back_2>" },
{"question_number":82, "stimulus": "X", "trial_type": "test", "trial_section": "<0_back_2>" },
{"question_number":83, "stimulus": "R", "trial_type": "test", "trial_section": "<0_back_2>" },
{"question_number":84, "stimulus": "Z", "trial_type": "test", "trial_section": "<0_back_2>" },
{"question_number":85, "stimulus": "W", "trial_type": "test", "trial_section": "<0_back_2>" },
{"question_number":86, "stimulus": "X", "trial_type": "test", "trial_section": "<0_back_2>" },
{"question_number":87, "stimulus": "Q", "trial_type": "test", "trial_section": "<0_back_2>" },
{"question_number":88, "stimulus": "M", "trial_type": "test", "trial_section": "<0_back_2>" },
{"question_number":89, "stimulus": "X", "trial_type": "test", "trial_section": "<0_back_2>" },
{"question_number":90, "stimulus": "X", "trial_type": "test", "trial_section": "<0_back_2>" }
]
}
